{
    "Mismatch Keywords" : [
        "Mismatch in End dates",
        "Mismatch in Start dates",
        "Not Applicable",
        "Project Start Date is in the past",
        "Customer/Project Code is Blank",
        "Task is Blank",
        "Error",
        "Project Start Date is Blank",
        "Project End Date is Blank",
        "Project Location is Blank",
        "Project Manager is Blank",
        "Service Item is Blank",
        "Error - Time entered before Project Start Date",
        "Error - Time entered beyond Project End Date",
        "FALSE",
        "Status not Internal",
        "Start and End Date not within this Fiscal Year",
        "Project Type is not non-Billable",
        "LOB is not NA",
        "PM is blank",
        "Op status not 99",
        "Backlog type is not internal",
        "A resource is allocated",
        "Time is allocated to Resource",
        "not all required preferences checked for Internal",
        "not all required preferences checked for Expenses",
        "not all required preferences checked for Sales",
        "not all required preferences checked for TimeOff",
        "Project Start Date is in the past",
        "Expected Close in the past",
        "Project Start Date is not on or after Expected Close",
        "Start Date occurs after End Date",
        "mismatch in backlog and opp status",
        "Needs Review",
        "Projected Total not zero",
        "Sales Rep to be updated",
        "MISMATCH",
        "Check",
        "Project Type is Blank",
        "FOREX is Blank",
        "Company Audit Name Mismatch",
        "Subsidiary Mismatch",
        "LOB Mismatch",
        "mismatch in location",
        "Mismatch in Start Date",
        "Mismatch in End Date",
        "Mismatch in Audit Name",
        "Mismatch in Project Status",
        "Mismatch in Opportunity Status",
        "Mismatch in Backlog type",
        "Mismatch",
        "Mismatch in GEO",
        "Mismatch in Project Type",
        "Mismatch in Project Audit Name",
        "Mismatch in Backlog Type",
        "Mismatch in LOB",
        "Mismatch in Status",
        "Mismatch in Sales Rep",
        "Mismatch in Client Short Audit Name",
        "Mismatch in Currency",
        "Mismatch in ID",
        "Mismatch in Customer Account Tier",
        "Mismatch in Forex Rate",
        "not Tentative project",
        "not all required preferences checked",
        "Rev Rule Mismatch",
        "No External ID",
        "No Project Manager",
        "Rev Rule Mismatch",
        "CHECK",
        "Error - Time entered beyond Project End Date",
        "Error - Time entered before Project Start Date"
    ],
    "Audits" : [
        {
            "Audit Name": "Logic - Audit - Project vs Revenue Schedule Record - Meta Data",
            "Excel Name without Ext": "LogicAuditProjectvsRevenueScheduleRecordMetaDataResults",
            "Table Sheet Name Mapping": {
                "DW_AUDT.FINAL_PROJECT_VS_REVENUE_SCH_REC_META_DATA": ""
            }
        },
        {
            "Audit Name": "Logic - Audit - Opportunity vs Projects Record",
            "Excel Name without Ext": "LogicAuditOpportunityvsProjectsRecordResults",
            "Table Sheet Name Mapping": {
                "DW_AUDT.FINAL_OPPO_VS_PROJ_REC": ""
            }
        },
        {
            "Audit Name": "Logic - Audit - Contract TCV vs Opportunity TCV",
            "Excel Name without Ext": "LogicAuditContractTCVvsOpportunityTCVResults",
            "Table Sheet Name Mapping": {
                "DW_AUDT.FINAL_CONTRACT_TCV_VS_OPPO_TCV_1": "LogicAuditContractTCVvsOpportun",
                "DW_AUDT.FINAL_CONTRACT_TCV_VS_OPP_TCV": "Contract TCV vs Opportunity TCV"
            }
        },
        {
            "Audit Name": "Logic - Audit - Opportunity in Status 01- 08",
            "Excel Name without Ext": "LogicAuditOpportunityinStatus0108Results",
            "Table Sheet Name Mapping": {
                "DW_AUDT.FINAL_OPPO_STATUS_01_08": ""
            }
        },
        {
            "Audit Name": "Logic - Audit - Opportunities [Status 07 - 10], Contracts",
            "Excel Name without Ext": "LogicAuditOpportunitiesStatus0710ContractsResults",
            "Table Sheet Name Mapping": {
                "DW_AUDT.FINAL_OPPO_STATUS_07_10_CONTRACTS": ""
            }
        },
        {
            "Audit Name": "Logic - Audit - Opportunities Pending PD",
            "Excel Name without Ext": "LogicAuditOpportunitiesPendingPDResults",
            "Table Sheet Name Mapping": {
                "DW_AUDT.FINAL_OPPO_PENDING_PD": ""
            }
        },
        {
            "Audit Name": "Logic - Audit - Client Projects with Opportunity [Status 04 - 08]",
            "Excel Name without Ext": "LogicAuditClientProjectswithOpportunityStatus0408Results",
            "Table Sheet Name Mapping": {
                "DW_AUDT.FINAL_PROJ_OPPO_STATUS_04_08": ""
            }
        },
        {
            "Audit Name": "Logic - Audit - Client Projects with Opportunity [Status 09 - 10]",
            "Excel Name without Ext": "LogicAuditClientProjectswithOpportunityStatus0910Results",
            "Table Sheet Name Mapping": {
                "DW_AUDT.FINAL_PROJ_OPPO_STATUS_09_10": ""
            }
        },
        {
            "Audit Name": "Logic - Audit - Internal Projects without Preferences",
            "Excel Name without Ext": "LogicAuditInternalProjectswithoutPreferencesResults",
            "Table Sheet Name Mapping": {
                "DW_AUDT.FINAL_INTERNAL_PROJ_WITHOUT_PREFERENCES": ""
            }
        },
        {
            "Audit Name": "Logic - Audit - Internal Projects (Bench And Not Applicable) with Preferences",
            "Excel Name without Ext": "LogicAuditInternalProjectsBenchAndNotApplicablewithPreferencesResults",
            "Table Sheet Name Mapping": {
                "DW_AUDT.FINAL_INT_PROJ_BENCH_NOT_APPLICABLE_WITH_PREFERENCES": ""
            }
        },
        {
            "Audit Name": "Logic - Audit - Internal Projects (Expenses) with Preferences",
            "Excel Name without Ext": "LogicAuditInternalProjectsExpenseswithPreferencesResults",
            "Table Sheet Name Mapping": {
                "DW_AUDT.FINAL_INT_PROJ_EXPENSES_WITH_PREFERENCES": ""
            }
        },
        {
            "Audit Name": "Logic - Audit - Internal Projects (Sales) with Preferences",
            "Excel Name without Ext": "LogicAuditInternalProjectsSaleswithPreferencesResults",
            "Table Sheet Name Mapping": {
                "DW_AUDT.FINAL_INT_PROJ_SALES_WITH_PREFS": ""
            }
        },
        {
            "Audit Name": "Logic - Audit - Internal Projects (Strategic Initiative) with Preferences",
            "Excel Name without Ext": "LogicAuditInternalProjectsStrategyInitativewithPreferencesResults",
            "Table Sheet Name Mapping": {
                "DW_AUDT.FINAL_INT_PROJ_STRAT_INI_WITH_PREFS": ""
            }
        },
        {
            "Audit Name": "Logic - Audit - Internal Projects (Time Off) with Preferences",
            "Excel Name without Ext": "LogicAuditInternalProjectsTimeOffwithPreferencesResults",
            "Table Sheet Name Mapping": {
                "DW_AUDT.FINAL_INT_PROJ_TIM_OFF_WITH_PREFS": ""
            }
        },
        {
            "Audit Name": "Logic - Audit - Timesheet Submitted and Approved for Future Weeks",
            "Excel Name without Ext": "LogicAuditTimesheetSubmittedandApprovedforFutureWeeksResults",
            "Table Sheet Name Mapping": {
                "DW_AUDT.FINAL_TIMSHT_SUB_AND_APP_FOR_FUT_WKS": ""
            }
        },
        {
            "Audit Name": "Logic - GBS - Timesheets to delete (Prior Hire Date or Post Exit Date)",
            "Excel Name without Ext": "LogicGBSTimesheetstodeletePriorHireDateorPostExitDateResults",
            "Table Sheet Name Mapping": {
                "DW_AUDT.FINAL_TIMSHT_TO_DLT_PRIOR_HIRE_DT_POST_EXIT_DT": ""
            }
        },
        {
            "Audit Name": "Logic - Audit - Time Day Wise Entries - Timesheets pending approval",
            "Excel Name without Ext": "LogicAuditTimeDayWiseEntriesResults",
            "Table Sheet Name Mapping": {
                "DW_AUDT.FINAL_TIM_DAY_WISE_ENTRIES": ""
            }
        },
        {
            "Audit Name": "Logic - Audit - RM - Resource Allocation by Project",
            "Excel Name without Ext": "Logic - Audit - RM - Resource Allocation by Project",
            "Table Sheet Name Mapping": {
                "DW_AUDT.FINAL_ALLOC_BEFORE_PROJ_SDATE": "Audit -Alloc before proj SDate",
                "DW_AUDT.FINAL_ALLOC_AFTER_PROJ_EDATE": "Audit-Alloc After proj EDate",
                "DW_AUDT.FINAL_INACTIVE_BUT_ALLOC": "Audit-Inactive but Alloc"
            }
        },
        {
            "Audit Name": "Logic - Audit - RM - Resource Allocation Not Equal to 40 Hrs based on Time",
            "Excel Name without Ext": "Logic - Audit - RM - Resource Allocation Not Equal to 40 Hrs based on Time",
            "Table Sheet Name Mapping": {
                "DW_AUDT.FINAL_EMP_WITH_NO_ALLOC": "Audit - Emp with No Alloc",
                "DW_AUDT.FINAL_EMP_ALLOC_UNDER_40": "Audit - Emp Alloc under 40 Hrs",
                "DW_AUDT.FINAL_EMP_ALLOC_OVER_40": "Audit - Emp Alloc over 40 Hrs"
            }
        },
        {
            "Audit Name": "Audit - Generic Resources Allocation",
            "Excel Name without Ext": "Logic - DB - RM - Generic Resource Allocated to Projects",
            "Table Sheet Name Mapping": {
                "DW_AUDT.FINAL_GEN_RESOURCES_ALLOC": ""
            }
        },
        {
            "Audit Name": "Audit - Cancelled-Closed Projects",
            "Excel Name without Ext": "df_FINAL_CANCEL_CLOSED_PRJ",
            "Table Sheet Name Mapping": {
                "DW_AUDT.FINAL_CANCEL_CLOSED_PRJ": ""
            }
        },
        {
            "Audit Name": "Audit - Project with No Allocation",
            "Excel Name without Ext": "Logic - Audit - RM - Projects with No Allocation",
            "Table Sheet Name Mapping": {
                "DW_AUDT.FINAL_PRJ_WITH_NO_ALLOC": ""
            }
        },
        {
            "Audit Name": "Audit - Allocated but unassigned",
            "Excel Name without Ext": "df_FINAL_ALLOC_BUT_UNASSIGNED",
            "Table Sheet Name Mapping": {
                "DW_AUDT.FINAL_ALLOC_BUT_UNASSIGNED": ""
            }
        },
        {
            "Audit Name": "LIS || Charges Forecast - Fixed Price, Recurring",
            "Excel Name without Ext": "Audit - Revenue Schedule vs Charges - Fixed Price Recurring projects",
            "Table Sheet Name Mapping": {
                "DW_AUDT.FINAL_REV_VS_CHGS_FIXEDPRICE_RECURRING": ""
            }
        },
        {
            "Audit Name": "LIS || Charges Forecast - Time And Material",
            "Excel Name without Ext": "Audit - Revenue Schedule vs Charges - Time & Material projects",
            "Table Sheet Name Mapping": {
                "DW_AUDT.FINAL_REV_VS_CHGS_TANDM": ""
            }
        },
        {
            "Audit Name": "LIS || Charges Forecast - Stage 04 - 08",
            "Excel Name without Ext": "Audit - Revenue Schedule vs Charges - 04 - 08",
            "Table Sheet Name Mapping": {
                "DW_AUDT.FINAL_REV_VS_CHGS_04_08": "Revenue vs Charges 04-08",
                "DW_AUDT.FINAL_PROJ_IDS_04_08_NOT_IN_REV": "Proj IDs for 04-08 not in Rev"
            }
        },
        {
            "Audit Name": "LIS || Charges Forecast - Fixed Bid, Milestone",
            "Excel Name without Ext": "Audit - Revenue Schedule vs Charges - Fixed Bid Milestone projects",
            "Table Sheet Name Mapping": {
                "DW_AUDT.FINAL_REV_VS_CHGS_FIXEDBID_MILESTONE": "Revenue vs Charges FB Milestone",
                "DW_AUDT.FINAL_PROJ_IDS_09_10_NOT_IN_REV": "Proj IDs for FP Recurring in Rev"
            }
        }
    ],
    "Background Color": "yellow",
    "Credentials": {
        "user": "SAMICHYASHRESTHA",
        "password": "LIS@winter22",
        "account": "thb67716.us-east-1",
        "warehouse": "LOGICBIPRD",
        "database": "LOGICBI_PRD",
        "schema": "DW_AUDT",
        "role": "SYSADMIN"
    }
}
